{
  "organisasi": {
    "nama": "SMA Negeri 1 Jakarta - OSIS",
    "tahunBerdiri": 2020,
    "email": "osis@sman1jakarta.sch.id",
    "telepon": "(021) 1234-5678",
    "alamat": "Jl. Sudirman No. 1, Jakarta Pusat",
    
    "sejarah": "OSIS SMA Negeri 1 Jakarta didirikan pada tahun 2020 dengan tujuan untuk menjadi wadah bagi siswa-siswi dalam mengembangkan potensi diri dan berkontribusi untuk kemajuan sekolah. Sejak berdiri, OSIS telah berhasil menyelenggarakan berbagai program unggulan yang mendapat dukungan penuh dari seluruh warga sekolah.",
    "visi": "Menjadi organisasi siswa yang unggul dalam membangun karakter, mengembangkan prestasi, dan berkontribusi nyata untuk kemajuan sekolah dan masyarakat.",
    "misi": [
      "Mengembangkan potensi siswa melalui berbagai program kegiatan yang bermanfaat",
      "Meningkatkan partisipasi siswa dalam kegiatan sekolah dan masyarakat",
      "Membangun komunikasi yang baik antara siswa, guru, dan pihak sekolah"
    ]
  },

  "pembina": [
    {
      "id": 1,
      "nama": "Dra. Siti Aminah, M.Pd.",
      "posisi": "Pembina/Pendamping Putri",
      "jenis_kelamin": "Perempuan",
      "foto": "images/pembina-putri.jpg"
    },
    {
      "id": 2,
      "nama": "Drs. Ahmad Rahman, M.Pd.",
      "posisi": "Pembina/Pendamping Putra",
      "jenis_kelamin": "Laki-laki",
      "foto": "images/pembina-putra.jpg"
    }
  ],

  "pengurusInti": [
    {
      "id": 1,
      "nama": "Rina Sari",
      "posisi": "Ketua OSIS",
      "kelas": "XII IPA 1",
      "foto": "images/ketua.jpg"
    },
    {
      "id": 2,
      "nama": "Budi Santoso",
      "posisi": "Wakil Ketua",
      "kelas": "XII IPS 2",
      "foto": "images/wakil-ketua.jpg"
    }
  ],

  "biroAdministrasi": [
    {
      "id": 1,
      "nama": "Maya Putri",
      "posisi": "Sekretaris",
      "kelas": "XI IPA 2",
      "foto": "images/sekretaris-1.jpg"
    },
    {
      "id": 2,
      "nama": "Dian Anggraini",
      "posisi": "Sekretaris",
      "kelas": "XI IPS 1",
      "foto": "images/sekretaris-2.jpg"
    }
  ],

  "biroKeuangan": [
    {
      "id": 1,
      "nama": "Andi Wijaya",
      "posisi": "Bendahara",
      "kelas": "XI IPA 1",
      "foto": "images/bendahara-1.jpg"
    },
    {
      "id": 2,
      "nama": "Sari Dewi",
      "posisi": "Bendahara",
      "kelas": "XI IPS 2",
      "foto": "images/bendahara-2.jpg"
    }
  ],

  "bidang": [
    {
      "id": 1,
      "nama": "Bidang Akademik & Prestasi",
      "deskripsi": "Bertanggung jawab dalam mengembangkan potensi akademik siswa dan meningkatkan prestasi sekolah melalui berbagai program bimbingan belajar dan kompetisi.",
      "icon": "fas fa-book",
      "ketua": {
        "nama": "Lina Kusuma",
        "kelas": "XII IPA 1",
        "foto": "images/bidang1-ketua.jpg"
      },
      "anggota": [
        {
          "nama": "Rizki Pratama",
          "kelas": "XI IPA 2",
          "foto": "images/bidang1-anggota1.jpg"
        },
        {
          "nama": "Siti Nurhaliza",
          "kelas": "XI IPS 1",
          "foto": "images/bidang1-anggota2.jpg"
        },
        {
          "nama": "Ahmad Fauzi",
          "kelas": "X IPA 1",
          "foto": "images/bidang1-anggota3.jpg"
        },
        {
          "nama": "Maya Sari",
          "kelas": "X IPS 2",
          "foto": "images/bidang1-anggota4.jpg"
        }
      ]
    },
    {
      "id": 2,
      "nama": "Bidang Kreativitas & Seni",
      "deskripsi": "Mengembangkan bakat seni dan kreativitas siswa melalui berbagai kegiatan kesenian, musik, dan pertunjukan seni.",
      "icon": "fas fa-palette",
      "ketua": {
        "nama": "Deni Rahman",
        "kelas": "XII IPS 1",
        "foto": "images/bidang2-ketua.jpg"
      },
      "anggota": [
        {
          "nama": "Putri Amelia",
          "kelas": "XI IPA 1",
          "foto": "images/bidang2-anggota1.jpg"
        },
        {
          "nama": "Bagus Setiawan",
          "kelas": "XI IPS 2",
          "foto": "images/bidang2-anggota2.jpg"
        },
        {
          "nama": "Rina Melati",
          "kelas": "X IPA 2",
          "foto": "images/bidang2-anggota3.jpg"
        },
        {
          "nama": "Eko Prasetyo",
          "kelas": "X IPS 1",
          "foto": "images/bidang2-anggota4.jpg"
        }
      ]
    },
    {
      "id": 3,
      "nama": "Bidang Olahraga & Kesehatan",
      "deskripsi": "Mendorong siswa untuk aktif dalam kegiatan olahraga dan menjaga kesehatan melalui berbagai program kebugaran dan kompetisi olahraga.",
      "icon": "fas fa-running",
      "ketua": {
        "nama": "Fajar Nugroho",
        "kelas": "XII IPA 2",
        "foto": "images/bidang3-ketua.jpg"
      },
      "anggota": [
        {
          "nama": "Intan Permata",
          "kelas": "XI IPA 3",
          "foto": "images/bidang3-anggota1.jpg"
        },
        {
          "nama": "Yoga Pratama",
          "kelas": "XI IPS 3",
          "foto": "images/bidang3-anggota2.jpg"
        },
        {
          "nama": "Dewi Lestari",
          "kelas": "X IPA 3",
          "foto": "images/bidang3-anggota3.jpg"
        },
        {
          "nama": "Rian Saputra",
          "kelas": "X IPS 3",
          "foto": "images/bidang3-anggota4.jpg"
        }
      ]
    },
    {
      "id": 4,
      "nama": "Bidang Sosial & Lingkungan",
      "deskripsi": "Berperan aktif dalam kegiatan sosial kemasyarakatan dan pelestarian lingkungan melalui berbagai program bakti sosial dan aksi peduli lingkungan.",
      "icon": "fas fa-heart",
      "ketua": {
        "nama": "Nadia Sari",
        "kelas": "XII IPS 2",
        "foto": "images/bidang4-ketua.jpg"
      },
      "anggota": [
        {
          "nama": "Adi Wijaya",
          "kelas": "XI IPA 4",
          "foto": "images/bidang4-anggota1.jpg"
        },
        {
          "nama": "Sari Indah",
          "kelas": "XI IPS 4",
          "foto": "images/bidang4-anggota2.jpg"
        },
        {
          "nama": "Bayu Santoso",
          "kelas": "X IPA 4",
          "foto": "images/bidang4-anggota3.jpg"
        },
        {
          "nama": "Maya Sari",
          "kelas": "X IPS 4",
          "foto": "images/bidang4-anggota4.jpg"
        }
      ]
    },
    {
      "id": 5,
      "nama": "Bidang Teknologi & Informasi",
      "deskripsi": "Mengembangkan kemampuan siswa di bidang teknologi informasi melalui berbagai workshop dan program digital literacy.",
      "icon": "fas fa-laptop",
      "ketua": {
        "nama": "Rizky Ramadhan",
        "kelas": "XII IPA 3",
        "foto": "images/bidang5-ketua.jpg"
      },
      "anggota": [
        {
          "nama": "Citra Dewi",
          "kelas": "XI IPA 5",
          "foto": "images/bidang5-anggota1.jpg"
        },
        {
          "nama": "Dika Pratama",
          "kelas": "XI IPS 5",
          "foto": "images/bidang5-anggota2.jpg"
        },
        {
          "nama": "Luna Sari",
          "kelas": "X IPA 5",
          "foto": "images/bidang5-anggota3.jpg"
        },
        {
          "nama": "Ardi Nugraha",
          "kelas": "X IPS 5",
          "foto": "images/bidang5-anggota4.jpg"
        }
      ]
    },
    {
      "id": 6,
      "nama": "Bidang Humas & Komunikasi",
      "deskripsi": "Mengelola komunikasi internal dan eksternal OSIS serta membangun citra positif organisasi melalui berbagai media komunikasi.",
      "icon": "fas fa-bullhorn",
      "ketua": {
        "nama": "Vina Amelia",
        "kelas": "XII IPS 3",
        "foto": "images/bidang6-ketua.jpg"
      },
      "anggota": [
        {
          "nama": "Raka Perdana",
          "kelas": "XI IPA 6",
          "foto": "images/bidang6-anggota1.jpg"
        },
        {
          "nama": "Tia Nurhaliza",
          "kelas": "XI IPS 6",
          "foto": "images/bidang6-anggota2.jpg"
        },
        {
          "nama": "Dimas Setiawan",
          "kelas": "X IPA 6",
          "foto": "images/bidang6-anggota3.jpg"
        },
        {
          "nama": "Rina Melati",
          "kelas": "X IPS 6",
          "foto": "images/bidang6-anggota4.jpg"
        }
      ]
    }
  ]
      ]
    },
    {
      "id": 3,
      "nama": "[NAMA BIDANG 3]",
      "deskripsi": "[DESKRIPSI BIDANG]",
      "icon": "fas fa-megaphone",
      "ketua": {
        "nama": "[NAMA KETUA BIDANG 3]",
        "kelas": "[KELAS]",
        "foto": "images/bidang3-ketua.jpg"
      },
      "anggota": [
        {
          "nama": "[NAMA ANGGOTA 1]",
          "kelas": "[KELAS]",
          "foto": "images/bidang3-anggota1.jpg"
        },
        {
          "nama": "[NAMA ANGGOTA 2]",
          "kelas": "[KELAS]",
          "foto": "images/bidang3-anggota2.jpg"
        },
        {
          "nama": "[NAMA ANGGOTA 3]",
          "kelas": "[KELAS]",
          "foto": "images/bidang3-anggota3.jpg"
        },
        {
          "nama": "[NAMA ANGGOTA 4]",
          "kelas": "[KELAS]",
          "foto": "images/bidang3-anggota4.jpg"
        }
      ]
    },
    {
      "id": 4,
      "nama": "[NAMA BIDANG 4]",
      "deskripsi": "[DESKRIPSI BIDANG]",
      "icon": "fas fa-star",
      "ketua": {
        "nama": "[NAMA KETUA BIDANG 4]",
        "kelas": "[KELAS]",
        "foto": "images/bidang4-ketua.jpg"
      },
      "anggota": [
        {
          "nama": "[NAMA ANGGOTA 1]",
          "kelas": "[KELAS]",
          "foto": "images/bidang4-anggota1.jpg"
        },
        {
          "nama": "[NAMA ANGGOTA 2]",
          "kelas": "[KELAS]",
          "foto": "images/bidang4-anggota2.jpg"
        },
        {
          "nama": "[NAMA ANGGOTA 3]",
          "kelas": "[KELAS]",
          "foto": "images/bidang4-anggota3.jpg"
        },
        {
          "nama": "[NAMA ANGGOTA 4]",
          "kelas": "[KELAS]",
          "foto": "images/bidang4-anggota4.jpg"
        }
      ]
    },
    {
      "id": 5,
      "nama": "[NAMA BIDANG 5]",
      "deskripsi": "[DESKRIPSI BIDANG]",
      "icon": "fas fa-trophy",
      "ketua": {
        "nama": "[NAMA KETUA BIDANG 5]",
        "kelas": "[KELAS]",
        "foto": "images/bidang5-ketua.jpg"
      },
      "anggota": [
        {
          "nama": "[NAMA ANGGOTA 1]",
          "kelas": "[KELAS]",
          "foto": "images/bidang5-anggota1.jpg"
        },
        {
          "nama": "[NAMA ANGGOTA 2]",
          "kelas": "[KELAS]",
          "foto": "images/bidang5-anggota2.jpg"
        },
        {
          "nama": "[NAMA ANGGOTA 3]",
          "kelas": "[KELAS]",
          "foto": "images/bidang5-anggota3.jpg"
        },
        {
          "nama": "[NAMA ANGGOTA 4]",
          "kelas": "[KELAS]",
          "foto": "images/bidang5-anggota4.jpg"
        }
      ]
    },
    {
      "id": 6,
      "nama": "[NAMA BIDANG 6]",
      "deskripsi": "[DESKRIPSI BIDANG]",
      "icon": "fas fa-lightbulb",
      "ketua": {
        "nama": "[NAMA KETUA BIDANG 6]",
        "kelas": "[KELAS]",
        "foto": "images/bidang6-ketua.jpg"
      },
      "anggota": [
        {
          "nama": "[NAMA ANGGOTA 1]",
          "kelas": "[KELAS]",
          "foto": "images/bidang6-anggota1.jpg"
        },
        {
          "nama": "[NAMA ANGGOTA 2]",
          "kelas": "[KELAS]",
          "foto": "images/bidang6-anggota2.jpg"
        },
        {
          "nama": "[NAMA ANGGOTA 3]",
          "kelas": "[KELAS]",
          "foto": "images/bidang6-anggota3.jpg"
        },
        {
          "nama": "[NAMA ANGGOTA 4]",
          "kelas": "[KELAS]",
          "foto": "images/bidang6-anggota4.jpg"
        }
      ]
    }
  ],

  "galeri": [
    {
      "id": 1,
      "judul": "[JUDUL FOTO]",
      "deskripsi": "[DESKRIPSI FOTO]",
      "kategori": "kegiatan",
      "foto": "images/galeri-1.jpg",
      "tanggal": "2024-01-15"
    },
    {
      "id": 2,
      "judul": "[JUDUL FOTO]",
      "deskripsi": "[DESKRIPSI FOTO]",
      "kategori": "profil",
      "foto": "images/galeri-2.jpg",
      "tanggal": "2024-01-14"
    },
    {
      "id": 3,
      "judul": "[JUDUL FOTO]",
      "deskripsi": "[DESKRIPSI FOTO]",
      "kategori": "acara",
      "foto": "images/galeri-3.jpg",
      "tanggal": "2024-01-13"
    }
  ],

  "socialMedia": {
    "instagram": "https://instagram.com/[USERNAME]",
    "facebook": "https://facebook.com/[USERNAME]",
    "youtube": "https://youtube.com/[USERNAME]",
    "twitter": "https://twitter.com/[USERNAME]"
  }
}
